{
  "nav-home": "Ana Sayfa",
  "nav-new": "Yeni Altın",
  "nav-used": "İkinci El Altın",
  "nav-gold-price": "Altın Fiyatı",
  "nav-currency-price": "Döviz Kurları",
  "new-gold-title": "En Son Altın Parçaları",
  "used-gold-title": "İkinci El Altın",
  "search-placeholder": "Ara...",
  "all-carats": "Tüm Ayarlar",
  "sort-default": "Varsayılan Sıralama",
  "sort-price-asc": "Fiyata Göre Artan",
  "sort-price-desc": "Fiyata Göre Azalan",
  "gold-price-title": "Altın Fiyatı",
  "gold-carat-prices": "Altın Ayar Fiyatları",
  "carat": "Ayar",
  "buy-price": "Alış Fiyatı",
  "sell-price": "Satış Fiyatı",
  "gold-gram-prices": "Gram ve Lira Fiyatları",
  "item": "Öğe",
  "price": "Fiyat",
  "gram-1": "1 Gram",
  "gram-5": "5 Gram",
  "gram-10": "10 Gram",
  "quarter-gold": "Çeyrek Lira",
  "half-gold": "Yarım Lira",
  "full-gold": "Tam Lira",
  "currency-rate-title": "Döviz Kurları",
  "currency": "Para Birimi",
  "address-title": "Adres",
  "tiktok-link": "TikTok Sayfası",
  "copyright": "© 2024 Al-Rajih Kuyumculuk. Tüm hakları saklıdır.",
  "admin-title": "Yönetim Paneli",
  "login-title": "Giriş",
  "username-label": "Kullanıcı Adı",
  "password-label": "Şifre",
  "login-button": "Giriş",
  "admin-dashboard": "Yönetim Paneli",
  "product-management": "Ürün Yönetimi",
  "existing-products": "Mevcut Ürünler",
  "gold-price-management": "Altın Fiyat Yönetimi",
  "currency-rate-management": "Döviz Kuru Yönetimi",
  "product-name-label": "Ürün Adı",
  "product-image-label": "Resim URL'si",
  "product-description-label": "Açıklama",
  "product-carat-label": "Ayar",
  "product-weight-label": "Ağırlık (Gram)",
  "product-price-label": "Fiyat (Türk Lirası)",
  "product-type-label": "Tip",
  "product-type-new": "Yeni",
  "product-type-used": "İkinci El",
  "product-save-button": "Ürünü Kaydet",
  "product-name": "Ad",
  "product-type": "Tip",
  "weight": "Ağırlık (g)",
  "actions": "İşlemler",
  "carat-21-buy-label": "Ayar 21 (Alış)",
  "carat-21-sell-label": "Ayar 21 (Satış)",
  "carat-22-buy-label": "Ayar 22 (Alış)",
  "carat-22-sell-label": "Ayar 22 (Satış)",
  "gram-1-buy-label": "1 Gram (Alış)",
  "gram-1-sell-label": "1 Gram (Satış)",
  "gram-5-buy-label": "5 Gram (Alış)",
  "gram-5-sell-label": "5 Gram (Satış)",
  "gram-10-buy-label": "10 Gram (Alış)",
  "gram-10-sell-label": "10 Gram (Satış)",
  "quarter-gold-buy-label": "Çeyrek Lira (Alış)",
  "quarter-gold-sell-label": "Çeyrek Lira (Satış)",
  "half-gold-buy-label": "Yarım Lira (Alış)",
  "half-gold-sell-label": "Yarım Lira (Satış)",
  "full-gold-buy-label": "Tam Lira (Alış)",
  "full-gold-sell-label": "Tam Lira (Satış)",
  "usd-buy-label": "USD (Alış)",
  "usd-sell-label": "USD (Satış)",
  "eur-buy-label": "EUR (Alış)",
  "eur-sell-label": "EUR (Satış)",
  "sar-buy-label": "SAR (Alış)",
  "sar-sell-label": "SAR (Satış)",
  "update-gold-prices-button": "Altın Fiyatlarını Güncelle",
  "update-currency-rates-button": "Döviz Kurlarını Güncelle",
  "edit-button": "Düzenle",
  "delete-button": "Sil",
  "confirm-delete": "Bu ürünü silmek istediğinizden emin misiniz?",
  "product-deleted": "Ürün başarıyla silindi!",
  "delete-failed": "Ürün silinemedi.",
  "please-login": "Lütfen giriş yapın.",
  "product-updated": "Ürün başarıyla güncellendi!",
  "product-added": "Ürün başarıyla eklendi!",
  "save-failed": "Ürün kaydedilemedi.",
  "error": "Bir hata oluştu.",
  "gold-prices-updated": "Altın fiyatları başarıyla güncellendi!",
  "gold-prices-failed": "Altın fiyatları güncellenemedi.",
  "currency-rates-updated": "Döviz kurları başarıyla güncellendi!",
  "currency-rates-failed": "Döviz kurları güncellenemedi."
}